hwrag/__init__.py
hwrag/embedding/__init__.py
hwrag/embedding/embedding.py
hwrag/evaluator/__init__.py
hwrag/evaluator/evaluator.py
hwrag/fusion/__init__.py
hwrag/fusion/fusion.py
hwrag/generator/__init__.py
hwrag/generator/generator.py
hwrag/llm/__init__.py
hwrag/llm/llm.py
hwrag/loader/__init__.py
hwrag/loader/loader.py
hwrag/refiner/__init__.py
hwrag/refiner/deduplicator.py
hwrag/refiner/filter.py
hwrag/reranker/__init__.py
hwrag/reranker/reranker.py
hwrag/splitter/__init__.py
hwrag/splitter/splitter.py
hwrag/vector/__init__.py
hwrag/vector/vector.py
tests/__init__.py
tests/unit/__init__.py
tests/unit/conftest.py
tests/unit/test_embedding.py
tests/unit/test_filter.py
tests/unit/test_llm.py
tests/unit/test_llm2.py
tests/unit/test_splitter.py
hwrag-0.0.5.dist-info/LICENSE
hwrag-0.0.5.dist-info/METADATA
hwrag-0.0.5.dist-info/WHEEL
hwrag-0.0.5.dist-info/top_level.txt
hwrag-0.0.5.dist-info/RECORD
